pygraphedit/__init__.py
pygraphedit/debug.py
pygraphedit/edit.py
pygraphedit/graph_physics.py
pygraphedit/graphics.py
pygraphedit/settings.py
pygraphedit/subscribe.py
pygraphedit/visual_graph.py
pygraphedit-0.0.5.dist-info/LICENSE
pygraphedit-0.0.5.dist-info/METADATA
pygraphedit-0.0.5.dist-info/WHEEL
pygraphedit-0.0.5.dist-info/top_level.txt
pygraphedit-0.0.5.dist-info/RECORD
