Metadata-Version: 2.1
Name: pygraphedit
Version: 0.0.5
Summary: Graph editor for Jupyter
Author: Andrii Kovryhin, Maksym Tur, Denis Logunov, Izabella Tylek
Project-URL: Homepage, https://github.com/EndRay/graph-editor
Project-URL: Issues, https://github.com/EndRay/graph-editor/issues
Classifier: Programming Language :: Python :: 3
Classifier: License :: OSI Approved :: MIT License
Classifier: Operating System :: OS Independent
Requires-Python: >=3.10
License-File: LICENSE
Requires-Dist: asttokens ==2.4.1
Requires-Dist: colorama ==0.4.6
Requires-Dist: comm ==0.2.0
Requires-Dist: decorator ==5.1.1
Requires-Dist: executing ==2.0.1
Requires-Dist: ipycanvas ==0.13.1
Requires-Dist: ipyevents ==2.0.2
Requires-Dist: ipython ==8.18.1
Requires-Dist: ipywidgets ==8.1.1
Requires-Dist: jedi ==0.19.1
Requires-Dist: jupyterlab-widgets ==3.0.9
Requires-Dist: matplotlib-inline ==0.1.6
Requires-Dist: networkx ==3.2.1
Requires-Dist: numpy ==1.26.2
Requires-Dist: parso ==0.8.3
Requires-Dist: Pillow ==10.1.0
Requires-Dist: prompt-toolkit ==3.0.41
Requires-Dist: pure-eval ==0.2.2
Requires-Dist: Pygments ==2.17.2
Requires-Dist: scipy ==1.11.4
Requires-Dist: six ==1.16.0
Requires-Dist: stack-data ==0.6.3
Requires-Dist: traitlets ==5.14.0
Requires-Dist: wcwidth ==0.2.12
Requires-Dist: widgetsnbextension ==4.0.9
Requires-Dist: pymunk ==6.6.0
